dask_lightgbm/__init__.py
dask_lightgbm/core.py
dask_lightgbm-0.2.0.dist-info/LICENSE
dask_lightgbm-0.2.0.dist-info/WHEEL
dask_lightgbm-0.2.0.dist-info/METADATA
dask_lightgbm-0.2.0.dist-info/RECORD
