Metadata-Version: 2.1
Name: dask-lightgbm
Version: 0.2.0
Summary: LightGBM distributed training on Dask
Home-page: https://github.com/dask/dask-lightgbm
License: BSD-3-Clause
Author: Jan Stiborek
Author-email: honza.stiborek@gmail.com
Requires-Python: >=3.6,<4.0
Classifier: Intended Audience :: Developers
Classifier: Intended Audience :: Science/Research
Classifier: License :: OSI Approved :: BSD License
Classifier: Programming Language :: Python :: 3
Classifier: Programming Language :: Python :: 3.6
Classifier: Programming Language :: Python :: 3.7
Classifier: Programming Language :: Python :: 3.8
Classifier: Programming Language :: Python :: 3.9
Classifier: Topic :: Scientific/Engineering
Classifier: Topic :: Software Development :: Libraries :: Python Modules
Classifier: Topic :: System :: Distributed Computing
Provides-Extra: sparse
Requires-Dist: dask (>=2.6.0,<3.0.0)
Requires-Dist: distributed (>=2.6.0,<3.0.0)
Requires-Dist: lightgbm (>=2.3.0,<3.0.0)
Requires-Dist: numpy (>=1.17.3,<2.0.0)
Requires-Dist: scipy (>=1.3.1,<2.0.0); extra == "sparse"
Requires-Dist: sparse (==0.5.0); extra == "sparse"
Requires-Dist: toolz (>=0.10.0,<0.11.0)
Project-URL: Repository, https://github.com/dask/dask-lightgbm
